{
    "Categories": [
        {
            "Category": "Fantasy",
            "CategoryNumber": 1
        },
        {
            "Category": "Action",
            "CategoryNumber": 2
        },
        {
            "Category": "Love",
            "CategoryNumber": 3
        },
        {
            "Category": "Drama",
            "CategoryNumber": 4
        },
        {
            "Category": "Comedy",
            "CategoryNumber": 5
        },
        {
            "Category": "Lifestyle",
            "CategoryNumber": 6
        },
        {
            "Category": "Politics",
            "CategoryNumber": 7
        },
        {
            "Category": "Food",
            "CategoryNumber": 8
        },
        {
            "Category": "History",
            "CategoryNumber": 9
        },
        {
            "Category": "Education",
            "CategoryNumber": 10
        }
    ]
}